pytimeline/__init__.py
pytimeline/__main__.py
pytimeline/structures.py
pytimeline/utils.py
pytimeline-0.3.0.dist-info/METADATA
pytimeline-0.3.0.dist-info/WHEEL
pytimeline-0.3.0.dist-info/entry_points.txt
pytimeline-0.3.0.dist-info/licenses/LICENSE
pytimeline-0.3.0.dist-info/RECORD
