Metadata-Version: 2.3
Name: pytimeline
Version: 0.3.0
Summary: A library for creating clean SVG timelines from JSON.
Project-URL: homepage, https://github.com/fsoubelet/Timeline
Project-URL: repository, https://github.com/fsoubelet/Timeline
Author-email: Felix Soubelet <felix.soubelet@cern.ch>
License-Expression: MIT
License-File: LICENSE
Keywords: Generator,SVG,Timeline
Classifier: Development Status :: 4 - Beta
Classifier: Intended Audience :: End Users/Desktop
Classifier: License :: OSI Approved :: MIT License
Classifier: Natural Language :: English
Classifier: Programming Language :: Python
Classifier: Programming Language :: Python :: 3 :: Only
Classifier: Programming Language :: Python :: 3.9
Classifier: Programming Language :: Python :: 3.10
Classifier: Programming Language :: Python :: 3.11
Classifier: Programming Language :: Python :: 3.12
Classifier: Programming Language :: Python :: Implementation :: CPython
Classifier: Topic :: Scientific/Engineering :: Visualization
Classifier: Topic :: Utilities
Requires-Python: >=3.9
Requires-Dist: click>=8.0
Requires-Dist: loguru>=0.5.3
Requires-Dist: pendulum>=2.1
Requires-Dist: svgwrite>=1.4
Provides-Extra: dev
Requires-Dist: black>=24.0; extra == 'dev'
Requires-Dist: isort>=5.10; extra == 'dev'
Requires-Dist: ruff>=0.5; extra == 'dev'
